{
	"wordlist": [
		{
			"lesson": "课文1",
			"words": "晨绒球汉艳服装扮读静停粗影"
		},
		{
			"lesson": "课文2",
			"words": "落荒笛舞狂罚假互所够猜扬臂"
		},
		{
			"lesson": "课文4",
			"words": "寒径斜霜赠刘盖菊残君橙送挑"
		},
		{
			"lesson": "课文5",
			"words": "铺泥晶紧院印排列规则乱棕迟"
		},
		{
			"lesson": "课文6",
			"words": "盒颜料票飘争仙闻梨勾油曲丰"
		},
		{
			"lesson": "课文8",
			"words": "柴冷旧裙怜饿乎焰蜡烛富诉离"
		},
		{
			"lesson": "课文10",
			"words": "旅咱救命拼扫胃管等刚流泪算"
		},
		{
			"lesson": "课文12",
			"words": "洞准备暴墙壁欲蜘蛛漂撞饱晒"
		},
		{
			"lesson": "课文15",
			"words": "搭亲父沙啦响羽翠嘴悄呑峨捕"
		},
		{
			"lesson": "课文16",
			"words": "蒲英盛耍喊欠钓而察拢趣喜睡"
		},
		{
			"lesson": "课文17",
			"words": "断楚至孤帆饮初镜未磨遥银盘"
		},
		{
			"lesson": "课文18",
			"words": "优淡浅错岩虾挺鼓数厚宝贵"
		},
		{
			"lesson": "课文19",
			"words": "滨灰渔遍躺载靠栽亚夏除踩洁"
		},
		{
			"lesson": "课文20",
			"words": "脑袋严实挡视线坛显材软刮库"
		},
		{
			"lesson": "课文21",
			"words": "妙演奏琴柔感受激击器滴敲鸣"
		},
		{
			"lesson": "课文22",
			"words": "朝雾蒙鼻总抖露湿吸猎翅膀重"
		},
		{
			"lesson": "课文23",
			"words": "刺冬颗忽暗伸句沟聪偷追腰"
		},
		{
			"lesson": "课文24",
			"words": "司庭登跌众弃持"
		},
		{
			"lesson": "课文25",
			"words": "掌班默腿轮投调摇晃烈勇"
		},
		{
			"lesson": "课文26",
			"words": "雀郊养粉谷粒男或者冻惜肯诚"
		}
	]
}
